twitter_scraper/__init__.py
twitter_scraper/scrape.py
wc_scrape-0.2.0.dist-info/METADATA
wc_scrape-0.2.0.dist-info/WHEEL
wc_scrape-0.2.0.dist-info/entry_points.txt
wc_scrape-0.2.0.dist-info/RECORD
