Metadata-Version: 2.1
Name: wc-scrape
Version: 0.2.0
Summary: A simple Twitter scraper
Author: William Chen
Author-email: wchen298@gmail.com
Requires-Python: >=3.12,<4.0
Classifier: Programming Language :: Python :: 3
Classifier: Programming Language :: Python :: 3.12
Requires-Dist: click (>=8.1.7,<9.0.0)
Requires-Dist: tweepy (>=4.14.0,<5.0.0)
Project-URL: Homepage, https://github.com/ouiliame/wc-scrape
